ms_enclave/__init__.py
ms_enclave/version.py
ms_enclave/cli/__init__.py
ms_enclave/cli/base.py
ms_enclave/cli/cli.py
ms_enclave/cli/start_server.py
ms_enclave/sandbox/__init__.py
ms_enclave/sandbox/boxes/__init__.py
ms_enclave/sandbox/boxes/base.py
ms_enclave/sandbox/boxes/docker_notebook.py
ms_enclave/sandbox/boxes/docker_sandbox.py
ms_enclave/sandbox/manager/__init__.py
ms_enclave/sandbox/manager/base.py
ms_enclave/sandbox/manager/http_manager.py
ms_enclave/sandbox/manager/local_manager.py
ms_enclave/sandbox/model/__init__.py
ms_enclave/sandbox/model/base.py
ms_enclave/sandbox/model/config.py
ms_enclave/sandbox/model/constants.py
ms_enclave/sandbox/model/requests.py
ms_enclave/sandbox/model/responses.py
ms_enclave/sandbox/server/__init__.py
ms_enclave/sandbox/server/server.py
ms_enclave/sandbox/tools/__init__.py
ms_enclave/sandbox/tools/base.py
ms_enclave/sandbox/tools/sandbox_tool.py
ms_enclave/sandbox/tools/tool_info.py
ms_enclave/sandbox/tools/sandbox_tools/__init__.py
ms_enclave/sandbox/tools/sandbox_tools/file_operation.py
ms_enclave/sandbox/tools/sandbox_tools/multi_code_executor.py
ms_enclave/sandbox/tools/sandbox_tools/notebook_executor.py
ms_enclave/sandbox/tools/sandbox_tools/python_executor.py
ms_enclave/sandbox/tools/sandbox_tools/shell_executor.py
ms_enclave/utils/__init__.py
ms_enclave/utils/json_schema.py
ms_enclave/utils/logger.py
ms_enclave-0.0.4.dist-info/licenses/LICENSE
ms_enclave-0.0.4.dist-info/METADATA
ms_enclave-0.0.4.dist-info/WHEEL
ms_enclave-0.0.4.dist-info/entry_points.txt
ms_enclave-0.0.4.dist-info/top_level.txt
ms_enclave-0.0.4.dist-info/RECORD
