Metadata-Version: 2.4
Name: ms-enclave
Version: 0.0.4
Summary: Modularized and Stable Sandbox runtime environment.
Author: ModelScope team
Author-email: contact@modelscope.cn
License: Apache License 2.0
Project-URL: Homepage, https://github.com/modelscope/ms-enclave
Keywords: python,llm,sandbox
Requires-Python: >=3.10
License-File: LICENSE
Requires-Dist: fastapi>=0.104.0
Requires-Dist: uvicorn[standard]>=0.24.0
Requires-Dist: openai
Requires-Dist: pydantic>=2.11.7
Requires-Dist: requests>=2.32.4
Requires-Dist: shortuuid>=1.0.13
Requires-Dist: aiohttp>=3.8.1
Requires-Dist: docstring-parser
Provides-Extra: dev
Requires-Dist: pytest>=8.3.5; extra == "dev"
Requires-Dist: pytest-asyncio>=0.23.0; extra == "dev"
Requires-Dist: pre-commit>=4.2.0; extra == "dev"
Requires-Dist: jupyter-book>=1.0.4.post1; extra == "dev"
Requires-Dist: pytest-cov>=6.2.1; extra == "dev"
Provides-Extra: docker
Requires-Dist: docker>=7.1.0; extra == "docker"
Requires-Dist: websocket-client; extra == "docker"
Dynamic: license-file
